SRgenerator/SR_generator.py
SRgenerator/__init__.py
SRgenerator-0.1.1.dist-info/LICENSE.txt
SRgenerator-0.1.1.dist-info/METADATA
SRgenerator-0.1.1.dist-info/WHEEL
SRgenerator-0.1.1.dist-info/top_level.txt
SRgenerator-0.1.1.dist-info/RECORD
